zope/app/security/__init__.py
zope/app/security/_protections.py
zope/app/security/_protections.zcml
zope/app/security/basicauthadapter.py
zope/app/security/configure.zcml
zope/app/security/ftpauth.py
zope/app/security/globalmodules.zcml
zope/app/security/i18n.py
zope/app/security/interfaces.py
zope/app/security/loginpassword.py
zope/app/security/meta.zcml
zope/app/security/metaconfigure.py
zope/app/security/metadirectives.py
zope/app/security/permission.py
zope/app/security/principal.py
zope/app/security/principallogging.py
zope/app/security/principalregistry.py
zope/app/security/protectclass.py
zope/app/security/settings.py
zope/app/security/standardpermissions.zcml
zope/app/security/vocabulary.py
zope/app/security/browser/__init__.py
zope/app/security/browser/auth.py
zope/app/security/browser/authutilitysearchview.pt
zope/app/security/browser/authutilitysearchview.rst
zope/app/security/browser/configure.zcml
zope/app/security/browser/login.pt
zope/app/security/browser/login_failed.pt
zope/app/security/browser/loginlogout.rst
zope/app/security/browser/logout.pt
zope/app/security/browser/principalterms.py
zope/app/security/browser/redirect.pt
zope/app/security/browser/tests.py
zope/app/security/tests/__init__.py
zope/app/security/tests/ftesting.zcml
zope/app/security/tests/persistentlist.rst
zope/app/security/tests/test_basicauthadapter.py
zope/app/security/tests/test_doctests.py
zope/app/security/tests/test_ftpauth.py
zope/app/security/tests/test_interfaces.py
zope/app/security/tests/test_loginpassword.py
zope/app/security/tests/test_logout.py
zope/app/security/tests/test_permission.py
zope/app/security/tests/test_principal.py
zope/app/security/tests/test_principallogging.py
zope/app/security/tests/test_principalregistry.py
zope/app/security/tests/test_vocabulary.py
zope_app_security-8.0.dist-info/licenses/LICENSE.txt
zope_app_security-8.0.dist-info/METADATA
zope_app_security-8.0.dist-info/WHEEL
zope_app_security-8.0.dist-info/top_level.txt
zope_app_security-8.0.dist-info/RECORD
