Metadata-Version: 2.4
Name: zope.app.security
Version: 8.0
Summary: ZMI Views For Zope3 Security Components
Home-page: http://github.com/zopefoundation/zope.app.security
Author: Zope Foundation and Contributors
Author-email: zope-dev@zope.dev
License: ZPL-2.1
Keywords: zope security authentication principal ftp http
Classifier: Development Status :: 5 - Production/Stable
Classifier: Environment :: Web Environment
Classifier: Intended Audience :: Developers
Classifier: License :: OSI Approved :: Zope Public License
Classifier: Programming Language :: Python
Classifier: Programming Language :: Python :: 3
Classifier: Programming Language :: Python :: 3.9
Classifier: Programming Language :: Python :: 3.10
Classifier: Programming Language :: Python :: 3.11
Classifier: Programming Language :: Python :: 3.12
Classifier: Programming Language :: Python :: 3.13
Classifier: Programming Language :: Python :: Implementation :: CPython
Classifier: Programming Language :: Python :: Implementation :: PyPy
Classifier: Natural Language :: English
Classifier: Operating System :: OS Independent
Classifier: Topic :: Internet :: WWW/HTTP
Classifier: Framework :: Zope :: 3
Requires-Python: >=3.9
License-File: LICENSE.txt
Requires-Dist: setuptools
Requires-Dist: zope.app.localpermission
Requires-Dist: zope.app.pagetemplate
Requires-Dist: zope.app.publisher
Requires-Dist: zope.authentication
Requires-Dist: zope.i18n
Requires-Dist: zope.i18nmessageid
Requires-Dist: zope.interface
Requires-Dist: zope.principalregistry
Requires-Dist: zope.publisher>=4.3.1
Requires-Dist: zope.security
Requires-Dist: zope.securitypolicy
Requires-Dist: zope.login
Provides-Extra: test
Requires-Dist: zope.app.wsgi; extra == "test"
Requires-Dist: zope.testrunner>=6.4; extra == "test"
Requires-Dist: webtest; extra == "test"
Dynamic: author
Dynamic: author-email
Dynamic: classifier
Dynamic: description
Dynamic: home-page
Dynamic: keywords
Dynamic: license
Dynamic: license-file
Dynamic: provides-extra
Dynamic: requires-dist
Dynamic: requires-python
Dynamic: summary
